a79/__init__.py
a79/client.py
a79/helpers/__init__.py
a79/helpers/config.py
a79/helpers/data_transformation_utils.py
a79/helpers/initialize_workflow.py
a79/helpers/sales_agent_utils.py
a79/helpers/sales_agent_utils_test.py
a79/helpers/tests/__init__.py
a79/helpers/tests/test_data_transformation_utils.py
a79/localtools/__init__.py
a79/localtools/human_feedback.py
a79/localtools/human_feedback_models.py
a79/models/__init__.py
a79/models/core.py
a79/models/enums.py
a79/models/tools/__init__.py
a79/models/tools/audio_models.py
a79/models/tools/call_task_generator_models.py
a79/models/tools/call_task_output_parser_models.py
a79/models/tools/chart_models.py
a79/models/tools/chorus_models.py
a79/models/tools/citation_models.py
a79/models/tools/clinical_trials_search_models.py
a79/models/tools/composio_models.py
a79/models/tools/datasource_models.py
a79/models/tools/db_models.py
a79/models/tools/document_models.py
a79/models/tools/edgartool_models.py
a79/models/tools/email_models.py
a79/models/tools/excel_models.py
a79/models/tools/file_models.py
a79/models/tools/firecrawl_models.py
a79/models/tools/fireflies_models.py
a79/models/tools/folder_models.py
a79/models/tools/gmail_models.py
a79/models/tools/google_models.py
a79/models/tools/googlecalendar_models.py
a79/models/tools/googledrive_models.py
a79/models/tools/llm_models.py
a79/models/tools/operators_models.py
a79/models/tools/outlook_models.py
a79/models/tools/parallel_thread_process_models.py
a79/models/tools/perplexity_models.py
a79/models/tools/pii_models.py
a79/models/tools/pitchbook_models.py
a79/models/tools/podcast_models.py
a79/models/tools/project_models.py
a79/models/tools/proquest_models.py
a79/models/tools/pubmed_models.py
a79/models/tools/react_agent_models.py
a79/models/tools/roleplay_coaching_analyzer_models.py
a79/models/tools/salesforce_models.py
a79/models/tools/snowflake_models.py
a79/models/tools/sourcescrub_models.py
a79/models/tools/thoughtspot_models.py
a79/models/tools/workflow_models.py
a79-0.2.13.dist-info/METADATA
a79-0.2.13.dist-info/WHEEL
a79-0.2.13.dist-info/licenses/LICENSE
a79-0.2.13.dist-info/RECORD
