Metadata-Version: 2.4
Name: a79
Version: 0.2.13
Summary: A79 AI Python SDK
Project-URL: Repository, https://github.com/a79ai/a79
Author-email: A79 AI <dev@a79.ai>
License-Expression: MIT
License-File: LICENSE
Classifier: Development Status :: 3 - Alpha
Classifier: Intended Audience :: Developers
Classifier: License :: OSI Approved :: MIT License
Classifier: Programming Language :: Python :: 3
Classifier: Programming Language :: Python :: 3.11
Requires-Python: >=3.9
Requires-Dist: numpy<3,>=1.24.0
Requires-Dist: pandas<3,>=2.0.0
Requires-Dist: pydantic==2.11.7
Requires-Dist: requests<3,>=2.32.3
Requires-Dist: sqlalchemy==2.0.30
